{
  "activityId": 21652916429,
  "activityUUID": {
    "uuid": "03f6075c-01c0-472a-842a-0b342085db79"
  },
  "activityName": "Treadmill Running",
  "userProfileId": 130724645,
  "isMultiSportParent": false,
  "activityTypeDTO": {
    "typeId": 18,
    "typeKey": "treadmill_running",
    "parentTypeId": 1,
    "isHidden": false,
    "restricted": false,
    "trimmable": true
  },
  "eventTypeDTO": {
    "typeId": 9,
    "typeKey": "uncategorized",
    "sortOrder": 10
  },
  "accessControlRuleDTO": {
    "typeId": 2,
    "typeKey": "private"
  },
  "timeZoneUnitDTO": {
    "unitId": 124,
    "unitKey": "Europe/Paris",
    "factor": 0.0,
    "timeZone": "Europe/Paris"
  },
  "metadataDTO": {
    "isOriginal": true,
    "deviceApplicationInstallationId": 1004838,
    "agentApplicationInstallationId": null,
    "agentString": null,
    "fileFormat": {
      "formatId": 7,
      "formatKey": "fit"
    },
    "associatedCourseId": null,
    "lastUpdateDate": "2026-01-24T18:27:24.0",
    "uploadedDate": "2026-01-24T18:27:24.0",
    "videoUrl": null,
    "hasPolyline": false,
    "hasChartData": true,
    "hasHrTimeInZones": true,
    "hasPowerTimeInZones": true,
    "userInfoDto": {
      "userProfilePk": 130724645,
      "displayname": "7a2851aa-2dbd-4229-8aa5-e7e850917dca",
      "fullname": "Tolga",
      "profileImageUrlLarge": "https://s3.amazonaws.com/garmin-connect-prod/profile_images/c15bfbe2-e142-4ff7-af67-c7119150542c-prof.png",
      "profileImageUrlMedium": "https://s3.amazonaws.com/garmin-connect-prod/profile_images/c15bfbe2-e142-4ff7-af67-c7119150542c-prfr.png",
      "profileImageUrlSmall": "https://s3.amazonaws.com/garmin-connect-prod/profile_images/c15bfbe2-e142-4ff7-af67-c7119150542c-prth.png",
      "userPro": false
    },
    "childIds": [],
    "childActivityTypes": [],
    "sensors": null,
    "activityImages": [],
    "manufacturer": "GARMIN",
    "diveNumber": null,
    "lapCount": 3,
    "associatedWorkoutId": null,
    "isAtpActivity": null,
    "deviceMetaDataDTO": {
      "deviceId": "3495286287",
      "deviceTypePk": 37125,
      "deviceVersionPk": 1004838
    },
    "hasIntensityIntervals": false,
    "hasSplits": true,
    "eBikeMaxAssistModes": null,
    "eBikeBatteryUsage": null,
    "eBikeBatteryRemaining": null,
    "eBikeAssistModeInfoDTOList": null,
    "hasRunPowerWindData": false,
    "calendarEventInfo": null,
    "groupRideUUID": null,
    "hasHeatMap": false,
    "personalRecord": false,
    "gcj02": false,
    "runPowerWindDataEnabled": false,
    "trimmed": false,
    "elevationCorrected": false,
    "manualActivity": false,
    "autoCalcCalories": false,
    "favorite": false
  },
  "summaryDTO": {
    "startTimeLocal": "2026-01-24T19:09:35.0",
    "startTimeGMT": "2026-01-24T18:09:35.0",
    "distance": 2004.34,
    "duration": 962.789,
    "movingDuration": 919.936,
    "elapsedDuration": 962.789,
    "averageSpeed": 2.0820000171661377,
    "averageMovingSpeed": 2.1787819540855646,
    "maxSpeed": 2.5469999313354488,
    "calories": 169.0,
    "bmrCalories": 24.0,
    "averageHR": 163.0,
    "maxHR": 189.0,
    "minHR": 101.0,
    "averageRunCadence": 151.0,
    "maxRunCadence": 165.0,
    "averageTemperature": 25.923349791942282,
    "maxTemperature": 29.0,
    "minTemperature": 24.0,
    "averagePower": 224.0,
    "maxPower": 273.0,
    "minPower": 0.0,
    "normalizedPower": 234.0,
    "totalWork": 51.55106658202109,
    "groundContactTime": 317.20001220703125,
    "strideLength": 85.62999877929688,
    "verticalOscillation": 8.55999984741211,
    "trainingEffect": 3.299999952316284,
    "anaerobicTrainingEffect": 1.0,
    "aerobicTrainingEffectMessage": "IMPACTING_TEMPO_22",
    "anaerobicTrainingEffectMessage": "MINOR_ANAEROBIC_BENEFIT_15",
    "verticalRatio": 10.010000228881836,
    "waterEstimated": 242.0,
    "trainingEffectLabel": "TEMPO",
    "minActivityLapDuration": 2.373,
    "directWorkoutFeel": 75,
    "directWorkoutRpe": 30,
    "moderateIntensityMinutes": 2,
    "vigorousIntensityMinutes": 13,
    "steps": 2432,
    "differenceBodyBattery": -4
  },
  "splitSummaries": [
    {
      "distance": 0.0,
      "duration": 8.0,
      "movingDuration": 0.0,
      "averageSpeed": 0.0,
      "maxSpeed": 0.0,
      "calories": 0.0,
      "bmrCalories": 0.0,
      "averageHR": 104.0,
      "maxHR": 106.0,
      "averageRunCadence": 0.0,
      "maxRunCadence": 0.0,
      "averageTemperature": 24.0,
      "maxTemperature": 24.0,
      "minTemperature": 24.0,
      "averagePower": 0.0,
      "maxPower": 0.0,
      "totalExerciseReps": 0,
      "splitType": "RWD_STAND",
      "noOfSplits": 1,
      "maxDistance": 0,
      "maxDistanceWithPrecision": 0.0,
      "avgStepFrequency": 0.0
    },
    {
      "distance": 1986.73,
      "duration": 946.0,
      "movingDuration": 910.0,
      "averageSpeed": 2.0999999046325684,
      "averageMovingSpeed": 2.1832197587568687,
      "maxSpeed": 2.5469999313354488,
      "calories": 167.0,
      "bmrCalories": 23.0,
      "averageHR": 163.0,
      "maxHR": 189.0,
      "averageRunCadence": 152.515625,
      "maxRunCadence": 165.0,
      "averageTemperature": 26.0,
      "maxTemperature": 29.0,
      "minTemperature": 24.0,
      "averagePower": 227.0,
      "maxPower": 273.0,
      "normalizedPower": 234.0,
      "groundContactTime": 316.0,
      "strideLength": 85.55999755859375,
      "verticalOscillation": 8.569999694824219,
      "verticalRatio": 10.020000457763672,
      "totalExerciseReps": 0,
      "splitType": "RWD_RUN",
      "noOfSplits": 1,
      "maxDistance": 1986,
      "maxDistanceWithPrecision": 1986.73,
      "avgStepFrequency": 152.515625,
      "avgStepLength": 855.5999755859375
    },
    {
      "distance": 17.62,
      "duration": 8.777,
      "movingDuration": 8.0,
      "averageSpeed": 2.006999969482422,
      "averageMovingSpeed": 2.202500104904175,
      "maxSpeed": 2.2209999561309814,
      "calories": 2.0,
      "bmrCalories": 0.0,
      "averageHR": 182.0,
      "maxHR": 184.0,
      "averageRunCadence": 125.21875,
      "maxRunCadence": 127.0,
      "averageTemperature": 28.0,
      "maxTemperature": 29.0,
      "minTemperature": 28.0,
      "averagePower": 184.0,
      "maxPower": 216.0,
      "normalizedPower": 241.0,
      "groundContactTime": 442.6000061035156,
      "strideLength": 93.15999755859376,
      "verticalOscillation": 7.819999694824219,
      "verticalRatio": 8.390000343322754,
      "totalExerciseReps": 0,
      "splitType": "RWD_WALK",
      "noOfSplits": 1,
      "maxDistance": 17,
      "maxDistanceWithPrecision": 17.62,
      "avgStepFrequency": 125.21875,
      "avgStepLength": 931.5999755859375
    }
  ]
}